nonebot_plugin_genshin_cos-0.3.5.dist-info/METADATA
nonebot_plugin_genshin_cos-0.3.5.dist-info/WHEEL
nonebot_plugin_genshin_cos-0.3.5.dist-info/entry_points.txt
nonebot_plugin_genshin_cos-0.3.5.dist-info/licenses/LICENSE
nonebot_plugin_genshin_cos/__init__.py
nonebot_plugin_genshin_cos/config.py
nonebot_plugin_genshin_cos/hoyospider.py
nonebot_plugin_genshin_cos/matcher.py
nonebot_plugin_genshin_cos/utils.py
nonebot_plugin_genshin_cos-0.3.5.dist-info/RECORD
