Metadata-Version: 2.1
Name: nonebot-plugin-genshin-cos
Version: 0.3.5
Summary: 米游社原神cos图获取
Author-Email: Cvandia <106718176+Cvandia@users.noreply.github.com>
License: MIT
Requires-Python: <4,>=3.9
Requires-Dist: nonebot-plugin-apscheduler>=0.1.3
Requires-Dist: nonebot-adapter-onebot>=2.2.0
Requires-Dist: nonebot2>=2.2.0
Requires-Dist: httpx>=0.19.0
Requires-Dist: aiofiles>=0.7.0
Requires-Dist: pathlib>=1.0.1
Requires-Dist: ujson>=5.5.0
